Workbook

Sheet RESUMEN GENERAL
B2: PLAN DE COMPRAS PRELIMINAR
B5: CLIENTE: | D5: CMP
B6: NRO DE OFERTA: | D6: 101-2026
B7: NOMBRE DE PROYECTO: | D7: AZA
B10: RESUMEN DE COSTOS
B12: ITEM | C12: DESCRIPCIÓN | D12: COSTO TOTAL | E12: MARGEN | F12: PRECIO | G12: PRECIO USD | I12: HH UF
B13: 1 | C13: Ingeniería y planificación | D13: =+'Ingeniería y Planificación'!G20 -> 3744000 | E13: 0.55 | F13: =+D13/(1-E13) -> 8320000 | G13: =F13/$H$24 -> 8757.8947 | I13: =F13/SUM('Ingeniería y Planificación'!E8:E15)/H25 -> 1.0299069
B14: 2 | C14: Adicionales | D14: =+Adicionales!I22 -> 0 | E14: 0.3 | F14: =+D14/(1-E14) -> 0 | G14: =F14/$H$24 -> 0
B15: 3 | C15: Integración Eléctrica | D15: =+'Integración Eléctrica'!G18 -> 1224000 | E15: 0.55 | F15: =+D15/(1-E15) -> 2720000 | G15: =F15/$H$24 -> 2863.1579
B16: 4 | C16: Equipos | D16: =+Equipos!K30 -> 21647926 | E16: 0.3 | F16: =+D16/(1-E16) -> 30925609 | G16: =F16/$H$24 -> 32553.272
B17: 5 | C17: Flete | D17: =+Flete!G14 -> 400000 | E17: 0.1 | F17: =+D17/(1-E17) -> 444444.44 | G17: =F17/$H$24 -> 467.83626
B18: 6 | C18: Montaje y Puesta en Marcha | D18: =+Montaje!G17 -> 0 | E18: 0.3 | F18: =+D18/(1-E18) -> 0 | G18: =F18/$H$24 -> 0
B19: 7 | C19: Otros: Viajes, visitas a terreno, levantamientos | D19: =+Otros!G16 -> 1130000 | E19: 0.1 | F19: =+D19/(1-E19) -> 1255555.6 | G19: =F19/$H$24 -> 1321.6374
C22: PRECIO OFERTA PROYECTO | D22: =+SUM(D13:D19) -> 28145926 | E22: =(F22-D22)/F22 -> 0.35542119 | F22: =+SUM(F13:F19) -> 43665609 | G22: =SUM(G13:G19) -> 45963.798
E24: USD | F24: =F22/H24 -> 45963.798 | H24: 950 | I24: Dólar
H25: 40800 | I25: UF
E28: Solo P&PEM | F28: Solo Equipos
C29: Costos de Equipos | D29: =+F16 -> 30925609 | E29: 0 | F29: =+D29 -> 30925609
C30: Programación y Puesta en Marcha | D30: =+F13+F15 -> 11040000 | E30: =+D30 -> 11040000 | F30: -
C31: Logística | D31: =+F17+F19 -> 1700000 | E31: =D31 -> 1700000 | F31: -
C33: Total | D33: =SUM(D29:D31) -> 43665609 | E33: =SUM(E29:E31) -> 12740000 | F33: =SUM(F29:F32) -> 30925609

Sheet Ingeniería y Planificación
B2: PLAN DE COMPRAS PRELIMINAR
B5: 1 | C5: Ingeniería y Planificación
B7: ITEM | C7: DESCRIPCIÓN | D7: UNIDAD | E7: CANTIDAD | F7: COSTO UNIT. | G7: COSTO
B8: 1.1 | C8: HH Ingeniero PCS7 | D8: HH | E8: 0 | F8: 25000 | G8: =+F8*E8 -> 0
B9: 1.2 | C9: HH Ingeniero SCADA | D9: HH | E9: 0 | F9: 20000 | G9: =+F9*E9 -> 0
B10: 1.4 | C10: HH Ingeniero PLC | D10: HH | E10: 90 | F10: 20000 | G10: =+F10*E10 -> 1800000 | H10: 2 Semanas programacion PLC+SCADA
B11: 1.5 | C11: HH PEM Ingeniero | D11: HH | E11: 36 | F11: 20000 | G11: =+F11*E11 -> 720000 | H11: 4 dias en terreno
B12: 1.7 | C12: HH Integracion Tecnico | D12: HH | E12: 36 | F12: 17000 | G12: =+F12*E12 -> 612000 | H12: 4 dias Integracion
B13: 1.8 | C13: HH Planimetria | D13: HH | E13: 27 | F13: 17000 | G13: =+F13*E13 -> 459000 | H13: 3 Dias planimetria
B14: 1.9 | C14: HH FAT | D14: HH | E14: 9 | F14: 17000 | G14: =+F14*E14 -> 153000 | H14: 1 Dia FAT
B15: 1.10 | D15: HH | E15: 0 | F15: 15000 | G15: =+F15*E15 -> 0
C20: ATRÁS (Resumen General) | F20: COSTO TOTAL | G20: =+SUM(G8:G17) -> 3744000

Sheet Adicionales
B2: PLAN DE COMPRAS PRELIMINAR
B5: 2 | C5: Manufactura | J5: USD
J6: ='RESUMEN GENERAL'!H24 -> 950
A7: 777777 | B7: ITEM | C7: DESCRIPCIÓN | D7: MLFB | E7: UNIDAD | F7: CANTIDAD | G7: COSTO UNIT USD | H7: COSTO UNIT CLP | I7: COSTO
B8: 2.01 | E8: CU | F8: 0 | G8: 0 | H8: =G8*$J$6 -> 0 | I8: =+H8*F8 -> 0
B9: 2.02 | E9: CU | F9: 0 | G9: 0 | H9: =G9*$J$6 -> 0 | I9: =+G9*F9 -> 0
B10: 2.03 | F10: 0 | G10: 0 | H10: =G10*$J$6 -> 0 | I10: =+G10*F10 -> 0
B11: 2.04 | F11: 0 | G11: 0 | H11: =G11*$J$6 -> 0 | I11: =+G11*F11 -> 0
B12: 2.05 | F12: 0 | G12: 0 | H12: =G12*$J$6 -> 0 | I12: =+G12*F12 -> 0
B13: 2.06 | F13: 0 | G13: 0 | H13: =G13*$J$6 -> 0 | I13: =+G13*F13 -> 0
B14: 2.07 | F14: 0 | G14: 0 | H14: =G14*$J$6 -> 0 | I14: =+G14*F14 -> 0
B15: 2.08 | F15: 0 | G15: 0 | H15: =G15*$J$6 -> 0 | I15: =+G15*F15 -> 0
B16: 2.09 | F16: 0 | G16: 0 | H16: =G16*$J$6 -> 0 | I16: =+G16*F16 -> 0
B17: 2.10 | F17: 0 | G17: 0 | H17: =G17*$J$6 -> 0 | I17: =+G17*F17 -> 0
G20: PESO TOTAL | I20: =+SUM(F8:F17) -> 0
C22: ATRÁS (Resumen General) | G22: COSTO TOTAL | I22: =+SUM(I8:I17) -> 0

Sheet Integración Eléctrica
B2: PLAN DE COMPRAS PRELIMINAR
B5: 3 | C5: Integración Eléctrica
B7: ITEM | C7: DESCRIPCIÓN | D7: UNIDAD | E7: CANTIDAD | F7: COSTO UNIT | G7: COSTO
B8: 3.01 | C8: Integracion | D8: HH | E8: 72 | F8: 17000 | G8: =F8*E8 -> 1224000 | I8: 4 días en el armado del tablero teniendo los materiales y planos
B9: 3.02 | D9: cu | E9: 0 | F9: 0 | G9: =F9*E9 -> 0 | I9: fungibles
B10: 3.03 | D10: cu | E10: 0 | F10: 0 | G10: =F10*E10 -> 0
B11: 3.04 | D11: cu | E11: 0 | F11: 0 | G11: =F11*E11 -> 0
B12: 3.05 | D12: cu | E12: 0 | F12: 0 | G12: =F12*E12 -> 0
B13: 3.06 | D13: cu | E13: 0 | F13: 0 | G13: =F13*E13 -> 0
D14: cu | E14: 0 | F14: 0 | G14: =F14*E14 -> 0
D15: cu | E15: 0 | F15: 0 | G15: =F15*E15 -> 0
C18: ATRÁS (Resumen General) | F18: COSTO TOTAL | G18: =+SUM(G8:G15) -> 1224000

Sheet Equipos
B2: PLAN DE COMPRAS PRELIMINAR
B5: 4 | D5: Equipos | K5: cambio usd | L5: =+'RESUMEN GENERAL'!H24 -> 950
B7: ITEM | C7: CÓDIGO | D7: DESCRIPCIÓN | E7: DESCUENTO | F7: LISTA | G7: UNIDAD | H7: CANTIDAD | I7: COSTO UNIT USD | J7: COSTO UNIT. CLP | K7: COSTO $ TOTAL
B8: 4.01 | C8: 6SL3210-1PE33-7AL0 | D8: SINAMICS PM240-2 IP20 FSG A 3AC 380-480V 200.00kW | E8: XG | F8: 37072.13 | G8: CU | H8: 1 | I8: =F8*(1-VLOOKUP(E8,$O$8:$P$19,2,FALSE)) -> 16682.458 | J8: =I8*$L$5 -> 15848336 | K8: =H8*J8 -> 15848336 | O8: Grupo | P8: Descuento
B9: 4.02 | C9: 6SL3244-0BB12-1PA1 | D9: SINAMICS CU240E-2 DP | E9: XG | F9: 954.51 | G9: CU | H9: 1 | I9: =F9*(1-VLOOKUP(E9,$O$8:$P$19,2,FALSE)) -> 429.5295 | J9: =I9*$L$5 -> 408053.02 | K9: =H9*J9 -> 408053.02 | P9: 0
B10: 4.03 | C10: 6SL3255-0AA00-4JA2 | D10: Intelligent Operator Panel IOP-2 | E10: XG | F10: 506.71 | G10: CU | H10: 1 | I10: =F10*(1-VLOOKUP(E10,$O$8:$P$19,2,FALSE)) -> 228.0195 | J10: =I10*$L$5 -> 216618.52 | K10: =H10*J10 -> 216618.52 | O10: X1 | P10: 41%
B11: 4.04 | C11: 6SL3256-0AP00-0JA0 | D11: Door mounting kit for IOP-2/BOP-2 incl. 5m connecting cable | E11: XG | F11: 102.33 | G11: CU | H11: 1 | I11: =F11*(1-VLOOKUP(E11,$O$8:$P$19,2,FALSE)) -> 46.0485 | J11: =I11*$L$5 -> 43746.075 | K11: =H11*J11 -> 43746.075 | O11: X3 | P11: 41%
B12: 4.05 | C12: 3NA3260 | D12: LV HRC fuse link, NH2 400A AC 500V/ DC 440V | E12: XG | F12: 71.47 | G12: CU | H12: 3 | I12: =F12*(1-VLOOKUP(E12,$O$8:$P$19,2,FALSE)) -> 32.1615 | J12: =I12*$L$5 -> 30553.425 | K12: =H12*J12 -> 91660.275 | O12: X4 | P12: 44%
B13: 4.06 | C13: 3RT1076-6AP36 | D13: CONTACTOR, 250KW/400V/AC-3 | E13: XD | F13: 7031 | G13: CU | H13: 1 | I13: =F13*(1-VLOOKUP(E13,$O$8:$P$19,2,FALSE)) -> 2742.09 | J13: =I13*$L$5 -> 2604985.5 | K13: =H13*J13 -> 2604985.5 | O13: ZF | P13: 41%
B14: 4.07 | C14: - | D14: TABLERO AUTOSOPORTADO METALICA 2000X1200X800MM IP55 | F14: 0 | G14: CU | H14: 1 | I14: 0 | J14: 1634527 | K14: =H14*J14 -> 1634527 | O14: ZG | P14: 44%
B15: 4.08 | D15: Fungibles | F15: 0 | G15: CU | H15: 1 | I15: =F15*(1-VLOOKUP(E15,$O$8:$P$19,2,FALSE)) -> 0 | J15: 800000 | K15: =H15*J15 -> 800000 | O15: XD | P15: 61%
B16: 4.09 | F16: 0 | G16: CU | H16: 0 | I16: =F16*(1-VLOOKUP(E16,$O$8:$P$19,2,FALSE)) -> 0 | J16: =I16*$L$5 -> 0 | K16: =H16*J16 -> 0 | O16: XG | P16: 55%
B17: 4.10 | F17: 0 | G17: CU | H17: 0 | I17: =F17*(1-VLOOKUP(E17,$O$8:$P$19,2,FALSE)) -> 0 | J17: =I17*$L$5 -> 0 | K17: =H17*J17 -> 0 | O17: 1¿ | P17: 55%
B18: 4.11 | F18: 0 | G18: CU | H18: 0 | I18: =F18*(1-VLOOKUP(E18,$O$8:$P$19,2,FALSE)) -> 0 | J18: =I18*$L$5 -> 0 | K18: =H18*J18 -> 0 | O18: 4¿ | P18: 52%
B19: 4.12 | F19: 0 | G19: CU | H19: 0 | I19: =F19*(1-VLOOKUP(E19,$O$8:$P$19,2,FALSE)) -> 0 | J19: =I19*$L$5 -> 0 | K19: =H19*J19 -> 0 | O19: 2¿ | P19: 52%
B20: 4.13 | F20: 0 | G20: CU | H20: 0 | I20: =F20*(1-VLOOKUP(E20,$O$8:$P$19,2,FALSE)) -> 0 | J20: =I20*$L$5 -> 0 | K20: =H20*J20 -> 0 | O20: YC | P20: 0.59
B21: 4.14 | F21: 0 | G21: CU | H21: 0 | I21: =F21*(1-VLOOKUP(E21,$O$8:$P$19,2,FALSE)) -> 0 | J21: =I21*$L$5 -> 0 | K21: =H21*J21 -> 0
B22: 4.15 | F22: 0 | G22: CU | H22: 0 | I22: =F22*(1-VLOOKUP(E22,$O$8:$P$19,2,FALSE)) -> 0 | J22: =I22*$L$5 -> 0 | K22: =H22*J22 -> 0
B23: 4.16 | F23: 0 | G23: CU | H23: 0 | I23: =F23*(1-VLOOKUP(E23,$O$8:$P$19,2,FALSE)) -> 0 | J23: =I23*$L$5 -> 0 | K23: =H23*J23 -> 0
B24: 4.17 | F24: 0 | G24: CU | H24: 0 | I24: =F24*(1-VLOOKUP(E24,$O$8:$P$19,2,FALSE)) -> 0 | J24: =I24*$L$5 -> 0 | K24: =H24*J24 -> 0
D30: ATRÁS (Resumen General) | I30: COSTO TOTAL | K30: =+SUM(K8:K24) -> 21647926

Sheet Flete
B2: PLAN DE COMPRAS PRELIMINAR
B5: 5.0 | C5: Flete
B7: ITEM | C7: DESCRIPCIÓN | D7: UNIDAD | E7: CANTIDAD | F7: COSTO UNIT. | G7: COSTO
B8: 5.01 | D8: C/U | E8: 1 | F8: 400000 | G8: =F8*E8 -> 400000
B9: 5.02 | D9: C/U | G9: =F9*E9 -> 0
B10: 5.03 | D10: C/U | G10: =F10*E10 -> 0
B11: 5.04 | D11: C/U | G11: =F11*E11 -> 0
B12: 5.05 | D12: C/U | G12: =F12*E12 -> 0
C14: ATRÁS (Resumen General) | F14: COSTO TOTAL | G14: =+SUM(G8:G12) -> 400000

Sheet Montaje
B2: PLAN DE COMPRAS PRELIMINAR
B5: 6 | C5: Montaje
B7: ITEM | C7: DESCRIPCIÓN | D7: UNIDAD | E7: CANTIDAD | F7: COSTO UNIT. | G7: COSTO | H7: 0.15
B8: 6.01 | C8: Mano de obra general | D8: Gal | E8: 1 | F8: 0 | G8: =+F8*E8 -> 0 | H8: =F8/(1-$H$7) -> 0
B9: 6.02 | C9: Alza hombre articulado | D9: Gal | E9: 1 | F9: 0 | G9: =+F9*E9 -> 0 | H9: =F9/(1-$H$7) -> 0
B10: 6.03 | C10: Materiales de montaje | D10: Gal | E10: 1 | F10: 0 | G10: =+F10*E10 -> 0 | H10: =F10/(1-$H$7) -> 0
B11: 6.04 | C11: Materiales de integración | D11: Gal | E11: 1 | F11: 0 | G11: =+F11*E11 -> 0 | H11: =F11/(1-$H$7) -> 0
B12: 6.05 | C12: Montaje mecánico (Marcos Muñoz) | D12: Gal | E12: 1 | F12: 0 | G12: =+F12*E12 -> 0 | H12: =F12/(1-$H$7) -> 0
B13: 6.06 | D13: HH | F13: 0 | G13: =+F13*E13 -> 0 | H13: =F13/(1-$H$7) -> 0
B14: 6.07 | D14: HH | F14: 0 | G14: =+F14*E14 -> 0 | H14: =F14/(1-$H$7) -> 0
C17: ATRÁS (Resumen General) | F17: COSTO TOTAL | G17: =+SUM(G8:G14) -> 0

Sheet Otros
B2: PLAN DE COMPRAS PRELIMINAR
B5: 7 | C5: Otros
B7: ITEM | C7: DESCRIPCIÓN | D7: UNIDAD | E7: CANTIDAD | F7: COSTO UNIT. | G7: COSTO
B8: 7.01 | C8: Estadia | D8: C/U | E8: 4 | F8: 100000 | G8: =+F8*E8 -> 400000 | I8: TERRENO: 1 Semana - 2 personas
B9: 7.02 | C9: Alimentación | D9: C/U | E9: 4 | F9: 50000 | G9: =+F9*E9 -> 200000
B10: 7.03 | C10: Combustible | D10: C/U | E10: 4 | F10: 20000 | G10: =+F10*E10 -> 80000
B11: 7.04 | C11: Arriendo vehiculo | D11: C/U | E11: 4 | F11: 50000 | G11: =+F11*E11 -> 200000
B12: 7.05 | C12: Pasajes Avion (incl. Transfer) | D12: C/U | E12: 1 | F12: 250000 | G12: =+F12*E12 -> 250000
B13: 7.06 | C13: EPP | D13: C/U | E13: 0 | F13: 200000 | G13: =+F13*E13 -> 0
B14: 7.07 | C14: Arriendo Departamento (Anual) | D14: C/U | E14: 0 | G14: =+F14*E14 -> 0
C16: ATRÁS (Resumen General) | F16: COSTO TOTAL | G16: =+SUM(G8:G14) -> 1130000

Sheet Listado
I1: Margen | J1: =+'RESUMEN GENERAL'!E16 -> 0.3
A2: N° | B2: DESCRIPCIÓN | C2: CANT. | D2: COSTO UNIT. | E2: C/U c/s | F2: COSTO TOTAL | G2: Shipping | I2: COSTO UNIT. CLP | J2: VALOR VENTA
A3: 1 | B3: =+Equipos!C8&" - "&Equipos!D8 -> 6SL3210-1PE33-7AL0 - SINAMICS PM240-2 IP20 FSG A 3AC 380-480V 200.00kW | C3: =+Equipos!H8 -> 1 | D3: =+I3/(1-$J$1) -> 22640479 | E3: =+Tabla6[[#This Row],[COSTO UNIT.]]+$F$15/COUNTA(B3:B14) -> 22640479 | F3: =Tabla6[[#This Row],[CANT.]]*Tabla6[[#This Row],[COSTO UNIT.]] -> 22640479 | G3: =+Tabla6[[#This Row],[CANT.]]*Tabla6[[#This Row],[C/U c/s]] -> 22640479 | I3: =+Equipos!J8 -> 15848336 | J3: =+I3/(1-$J$1) -> 22640479
A4: 2 | B4: =+Equipos!C9&" - "&Equipos!D9 -> 6SL3244-0BB12-1PA1 - SINAMICS CU240E-2 DP | C4: =+Equipos!H9 -> 1 | D4: =+I4/(1-$J$1) -> 582932.89 | E4: =+Tabla6[[#This Row],[COSTO UNIT.]]+$F$15/9 -> 582932.89 | F4: =Tabla6[[#This Row],[CANT.]]*Tabla6[[#This Row],[COSTO UNIT.]] -> 582932.89 | G4: =+Tabla6[[#This Row],[CANT.]]*Tabla6[[#This Row],[C/U c/s]] -> 582932.89 | I4: =+Equipos!J9 -> 408053.02 | J4: =+I4/(1-$J$1) -> 582932.89
A5: 3 | B5: =+Equipos!C10&" - "&Equipos!D10 -> 6SL3255-0AA00-4JA2 - Intelligent Operator Panel IOP-2 | C5: =+Equipos!H10 -> 1 | D5: =+I5/(1-$J$1) -> 309455.04 | E5: =+Tabla6[[#This Row],[COSTO UNIT.]]+$F$15/9 -> 309455.04 | F5: =Tabla6[[#This Row],[CANT.]]*Tabla6[[#This Row],[COSTO UNIT.]] -> 309455.04 | G5: =+Tabla6[[#This Row],[CANT.]]*Tabla6[[#This Row],[C/U c/s]] -> 309455.04 | I5: =+Equipos!J10 -> 216618.52 | J5: =+I5/(1-$J$1) -> 309455.04
A6: 4 | B6: =+Equipos!C11&" - "&Equipos!D11 -> 6SL3256-0AP00-0JA0 - Door mounting kit for IOP-2/BOP-2 incl. 5m connecting cable | C6: =+Equipos!H11 -> 1 | D6: =+I6/(1-$J$1) -> 62494.393 | E6: =+Tabla6[[#This Row],[COSTO UNIT.]]+$F$15/9 -> 62494.393 | F6: =Tabla6[[#This Row],[CANT.]]*Tabla6[[#This Row],[COSTO UNIT.]] -> 62494.393 | G6: =+Tabla6[[#This Row],[CANT.]]*Tabla6[[#This Row],[C/U c/s]] -> 62494.393 | I6: =+Equipos!J11 -> 43746.075 | J6: =+I6/(1-$J$1) -> 62494.393
A7: 5 | B7: =+Equipos!C12&" - "&Equipos!D12 -> 3NA3260 - LV HRC fuse link, NH2 400A AC 500V/ DC 440V | C7: =+Equipos!H12 -> 3 | D7: =+I7/(1-$J$1) -> 43647.75 | E7: =+Tabla6[[#This Row],[COSTO UNIT.]]+$F$15/9 -> 43647.75 | F7: =Tabla6[[#This Row],[CANT.]]*Tabla6[[#This Row],[COSTO UNIT.]] -> 130943.25 | G7: =+Tabla6[[#This Row],[CANT.]]*Tabla6[[#This Row],[C/U c/s]] -> 130943.25 | I7: =+Equipos!J12 -> 30553.425 | J7: =+I7/(1-$J$1) -> 43647.75
A8: 6 | B8: =+Equipos!C13&" - "&Equipos!D13 -> 3RT1076-6AP36 - CONTACTOR, 250KW/400V/AC-3 | C8: =+Equipos!H13 -> 1 | D8: =+I8/(1-$J$1) -> 3721407.9 | E8: =+Tabla6[[#This Row],[COSTO UNIT.]]+$F$15/9 -> 3721407.9 | F8: =Tabla6[[#This Row],[CANT.]]*Tabla6[[#This Row],[COSTO UNIT.]] -> 3721407.9 | G8: =+Tabla6[[#This Row],[CANT.]]*Tabla6[[#This Row],[C/U c/s]] -> 3721407.9 | I8: =+Equipos!J13 -> 2604985.5 | J8: =+I8/(1-$J$1) -> 3721407.9
A9: 7 | B9: =+Equipos!C14&" - "&Equipos!D14 -> - - TABLERO AUTOSOPORTADO METALICA 2000X1200X800MM IP55 | C9: =+Equipos!H14 -> 1 | D9: =+I9/(1-$J$1) -> 2335038.6 | E9: =+Tabla6[[#This Row],[COSTO UNIT.]]+$F$15/9 -> 2335038.6 | F9: =Tabla6[[#This Row],[CANT.]]*Tabla6[[#This Row],[COSTO UNIT.]] -> 2335038.6 | G9: =+Tabla6[[#This Row],[CANT.]]*Tabla6[[#This Row],[C/U c/s]] -> 2335038.6 | I9: =+Equipos!J14 -> 1634527 | J9: =+I9/(1-$J$1) -> 2335038.6
A10: 8 | B10: =+Equipos!C15&" - "&Equipos!D15 -> - Fungibles | C10: =+Equipos!H15 -> 1 | D10: =+I10/(1-$J$1) -> 1142857.1 | E10: =+Tabla6[[#This Row],[COSTO UNIT.]]+$F$15/9 -> 1142857.1 | F10: =Tabla6[[#This Row],[CANT.]]*Tabla6[[#This Row],[COSTO UNIT.]] -> 1142857.1 | G10: =+Tabla6[[#This Row],[CANT.]]*Tabla6[[#This Row],[C/U c/s]] -> 1142857.1 | I10: =+Equipos!J15 -> 800000 | J10: =+I10/(1-$J$1) -> 1142857.1
A11: 9 | B11: =+Equipos!C16&" - "&Equipos!D16 -> - | C11: =+Equipos!H16 -> 0 | D11: =+I11/(1-$J$1) -> 0 | E11: =+Tabla6[[#This Row],[COSTO UNIT.]]+$F$15/9 -> 0 | F11: =Tabla6[[#This Row],[CANT.]]*Tabla6[[#This Row],[COSTO UNIT.]] -> 0 | G11: =+Tabla6[[#This Row],[CANT.]]*Tabla6[[#This Row],[C/U c/s]] -> 0 | I11: =+Equipos!J16 -> 0 | J11: =+I11/(1-$J$1) -> 0
A12: 10 | B12: =+Equipos!C17&" - "&Equipos!D17 -> - | C12: =+Equipos!H17 -> 0 | D12: =+I12/(1-$J$1) -> 0 | E12: =+Tabla6[[#This Row],[COSTO UNIT.]]+$F$15/9 -> 0 | F12: =Tabla6[[#This Row],[CANT.]]*Tabla6[[#This Row],[COSTO UNIT.]] -> 0 | G12: =+Tabla6[[#This Row],[CANT.]]*Tabla6[[#This Row],[C/U c/s]] -> 0 | I12: =+Equipos!J17 -> 0 | J12: =+I12/(1-$J$1) -> 0
A13: 11 | I13: =+Equipos!J18 -> 0 | J13: =+I13/(1-$J$1) -> 0
A14: 12 | I14: =+Equipos!J19 -> 0 | J14: =+I14/(1-$J$1) -> 0
A15: 10 | B15: Shipping | C15: 1 | D15: =+I15/(1-$J$1) -> 0 | F15: =Tabla6[[#This Row],[CANT.]]*Tabla6[[#This Row],[COSTO UNIT.]] -> 0 | I15: 0 | J15: =+I15/(1-$J$1) -> 0
A16: Total
D18: Sin Shipping | F18: =SUM(F3:F14) -> 30925609 | G18: =SUM(G3:G14) -> 30925609
G20: 7286755.3
E24: 784110
A33: Ítem | B33: Cantidad
A34: 1 | B34: 1
A35: 2 | B35: 1
A36: 3 | B36: 1
A38: Total Implementación
A41: Ítem | B41: Cantidad
A42: 1 | B42: Por evento
